pitchfork-api/__init__.py
pitchfork-api/pitchfork.py
pitchfork_api/__init__.py
pitchfork_api/pitchfork.py
pitchfork_api-0.0.4.dist-info/METADATA
pitchfork_api-0.0.4.dist-info/RECORD
pitchfork_api-0.0.4.dist-info/WHEEL
pitchfork_api-0.0.4.dist-info/top_level.txt
tests/__init__.py
tests/test_pitchfork.py
