Metadata-Version: 2.1
Name: pitchfork-api
Version: 0.0.4
Summary: Unofficial API for pitchfork.com reviews, maintained version of pitchfork
Home-page: https://github.com/tejassharma96/pitchfork_api/
Author: Tejas Sharma
Author-email: tejas.s1996@gmail.com
License: LICENSE.txt
Platform: UNKNOWN
Classifier: License :: OSI Approved :: MIT License
Classifier: Operating System :: OS Independent
Classifier: Programming Language :: Python
Classifier: Programming Language :: Python :: 3.3
Classifier: Programming Language :: Python :: 3.4
Classifier: Programming Language :: Python :: 3.5
Classifier: Programming Language :: Python :: 3.6
Classifier: Programming Language :: Python :: 3.7
Classifier: Topic :: Internet :: WWW/HTTP :: Browsers
Classifier: Topic :: Internet :: WWW/HTTP :: Indexing/Search
Classifier: Topic :: Multimedia :: Sound/Audio
Classifier: Topic :: Utilities
Requires-Dist: beautifulsoup4
